MANIFEST.in
README.txt
setup.py
docs/HISTORY.txt
src/affinitic/__init__.py
src/affinitic.verifyinterface.egg-info/PKG-INFO
src/affinitic.verifyinterface.egg-info/SOURCES.txt
src/affinitic.verifyinterface.egg-info/dependency_links.txt
src/affinitic.verifyinterface.egg-info/entry_points.txt
src/affinitic.verifyinterface.egg-info/namespace_packages.txt
src/affinitic.verifyinterface.egg-info/not-zip-safe
src/affinitic.verifyinterface.egg-info/requires.txt
src/affinitic.verifyinterface.egg-info/top_level.txt
src/affinitic/verifyinterface/README.txt
src/affinitic/verifyinterface/__init__.py
src/affinitic/verifyinterface/tests/__init__.py
src/affinitic/verifyinterface/tests/test_docs.py
src/affinitic/verifyinterface/tests/test_module1.py
src/affinitic/verifyinterface/tests/test_module2.py