Metadata-Version: 1.0
Name: affinitic.verifyinterface
Version: 0.1
Summary: Verify interface contract for all implements/classImplements declaration
Home-page: http://hg.affinitic.be/affinitic.verifyinterface
Author: Affinitic
Author-email: jfroche@affinitic.be
License: GPL
Keywords: interface zope.interface
Platform: UNKNOWN
Classifier: Programming Language :: Python
Classifier: Topic :: Software Development :: Libraries :: Python Modules
